.DS_Store
bazzellpy/__init__.py
bazzellpy/functions.py
bazzellpy-1.0.2.dist-info/LICENSE
bazzellpy-1.0.2.dist-info/METADATA
bazzellpy-1.0.2.dist-info/WHEEL
bazzellpy-1.0.2.dist-info/top_level.txt
bazzellpy-1.0.2.dist-info/RECORD
