Metadata-Version: 2.1
Name: bazzellpy
Version: 1.0.2
Summary: IntelTechniques OSINT tools as callable functions in Python!
Home-page: UNKNOWN
Author: dmw94
Author-email: UNKNOWN
License: GPLv3
Keywords: osint,searching,scraping
Platform: UNKNOWN
Classifier: License :: OSI Approved
Classifier: Programming Language :: Python
Classifier: Programming Language :: Python :: 3
